CHANGELOG
CONTRIBUTING
LICENSE
MANIFEST.in
README.rst
setup.py
docs/Makefile
docs/analyze-jump.rst
docs/api.rst
docs/build-jump.rst
docs/california-2002-surface.csv
docs/colorado-2009-surface.csv
docs/conf.py
docs/index.rst
docs/install.rst
docs/make.bat
docs/olympic-ski-jump.rst
docs/real-jumps.rst
docs/sydney-measurements-2020.csv
docs/utah-2010-surface.csv
docs/washington-2004-surface.csv
docs/web-app.rst
docs/wisconsin-2015-surface.csv
skijumpdesign/__init__.py
skijumpdesign/app.py
skijumpdesign/functions.py
skijumpdesign/skiers.py
skijumpdesign/surfaces.py
skijumpdesign/trajectories.py
skijumpdesign/utils.py
skijumpdesign/version.py
skijumpdesign.egg-info/PKG-INFO
skijumpdesign.egg-info/SOURCES.txt
skijumpdesign.egg-info/dependency_links.txt
skijumpdesign.egg-info/entry_points.txt
skijumpdesign.egg-info/not-zip-safe
skijumpdesign.egg-info/requires.txt
skijumpdesign.egg-info/top_level.txt
skijumpdesign/assets/favicon.ico
skijumpdesign/assets/gtag_template.js
skijumpdesign/assets/logo-dark-background-225x225.png
skijumpdesign/assets/logo-dark-background-50x50.png
skijumpdesign/assets/logo-light-background-200x200.png
skijumpdesign/assets/skijump.css
skijumpdesign/tests/__init__.py
skijumpdesign/tests/slide-on-times.txt
skijumpdesign/tests/slide-on-traj.txt
skijumpdesign/tests/test_functions.py
skijumpdesign/tests/test_skiers.py
skijumpdesign/tests/test_surfaces.py
skijumpdesign/tests/test_trajectories.py
skijumpdesign/tests/test_utils.py