Metadata-Version: 2.1
Name: skijumpdesign
Version: 1.4.0
Summary: Ski Jump Design and Analysis Tool For Specified Equivalent Fall Height
Home-page: http://www.skijumpdesign.info
Author: Jason K. Moore, Bryn Cloud, Mont Hubbard
Author-email: moorepants@gmail.com
License: MIT
Project-URL: Web Application, http://www.skijumpdesign.info
Project-URL: Library Documentation, http://skijumpdesign.readthedocs.io
Project-URL: Source Code, https://gitlab.com/moorepants/skijumpdesign
Project-URL: Issue Tracker, https://gitlab.com/moorepants/skijumpdesign/issues
Keywords: engineering sports physics design analysis
Platform: UNKNOWN
Classifier: Development Status :: 5 - Production/Stable
Classifier: License :: OSI Approved :: MIT License
Classifier: Intended Audience :: Science/Research
Classifier: Operating System :: OS Independent
Classifier: Programming Language :: Python :: 3.6
Classifier: Programming Language :: Python :: 3.7
Classifier: Programming Language :: Python :: 3.8
Classifier: Topic :: Scientific/Engineering :: Physics
Requires-Python: >=3.6
Provides-Extra: dev
